{
  "articles": [
    {
      "id": "eph87-06-june-1987",
      "documentId": "eph87-06",
      "title": "JUNE 1987",
      "summary": "This document outlines the schedule of events for June and July 1987, organized by the SJAA. Key activities include a general meeting featuring a talk on UFOs, board meetings, an indoor astronomy class, several field expeditions for astronomical observation at Fremont Peak and Grant Ranch, and an annual membership picnic culminating in a star party.",
      "categories": [
        "Events",
        "Observing Events",
        "Meetings",
        "Astronomy Education"
      ],
      "keywords": [
        "SJAA",
        "June 1987",
        "July 1987",
        "Astronomy Events",
        "UFOs",
        "Field Expeditions",
        "Star Party",
        "Membership Picnic"
      ],
      "pageStart": null,
      "pageEnd": null
    },
    {
      "id": "eph87-06-field-of-view",
      "documentId": "eph87-06",
      "title": "FIELD OF VIEW",
      "summary": "The article outlines upcoming events for the San Jose Astronomical Association (SJAA), including a June 6th general meeting featuring Tom Gates discussing UFOs, and the annual picnic and star party on July 18th at Grant Ranch County Park. It also details a multi-day Yosemite Glacier Point Star Party and camping trip, encouraging members to register, bring telescopes for public viewing, and volunteer for activities like a slideshow.",
      "categories": [
        "Events",
        "News",
        "Public Outreach",
        "Observing Reports",
        "Camping"
      ],
      "keywords": [
        "SJAA",
        "General Meeting",
        "UFOs",
        "Tom Gates",
        "Picnic",
        "Star Party",
        "Grant Ranch County Park",
        "Yosemite",
        "Glacier Point",
        "Camping",
        "Public Viewing",
        "Amateur Astronomy",
        "Telescopes",
        "Registration"
      ],
      "pageStart": 2,
      "pageEnd": 2
    },
    {
      "id": "eph87-06-took-two-shots-got-no-ducks",
      "documentId": "eph87-06",
      "title": "TOOK TWO SHOTS, GOT NO DUCKS",
      "summary": "At a Fremont Peak star party, the author humorously encountered a \"useless\" Takahashi tripod leveling accessory, dubbed \"duck feet.\" These oversized, hinged aluminum plates provided minimal leveling adjustment, leading the author to mock their impracticality and the manufacturer's design choices for a product seemingly designed for an already level surface.",
      "categories": [
        "Equipment Review",
        "Humor",
        "Observing Report",
        "Astronomy Accessory"
      ],
      "keywords": [
        "Takahashi",
        "Tripod leveling",
        "Telescope accessory",
        "Star party",
        "Fremont Peak",
        "Duck feet",
        "Equipment critique"
      ],
      "pageStart": null,
      "pageEnd": null
    },
    {
      "id": "eph87-06-employment-opportunities",
      "documentId": "eph87-06",
      "title": "EMPLOYMENT OPPORTUNITIES",
      "summary": "Orion Telescope Center is opening a new astronomy store in Cupertino early this Summer and is actively seeking full-time and part-time Customer Service Representatives. Interested applicants should send their inquiries to David English, Customer Service Manager, at the provided Santa Cruz address.",
      "categories": [
        "Employment",
        "Job Opportunities",
        "Business News",
        "Retail",
        "Astronomy Industry"
      ],
      "keywords": [
        "Orion Telescope Center",
        "Employment",
        "Job openings",
        "Customer Service Representative",
        "Cupertino",
        "Astronomy store",
        "Hiring",
        "Retail jobs",
        "Santa Cruz"
      ],
      "pageStart": null,
      "pageEnd": null
    },
    {
      "id": "eph87-06-grant-ranch-star-parties",
      "documentId": "eph87-06",
      "title": "GRANT RANCH STAR PARTIES",
      "summary": "The San Jose Astronomical Association (SJAA) is hosting star parties at Grant Ranch County Park, offering a convenient, close-to-home observing location. The article provides detailed directions to the park, located on Mt. Hamilton Road, along with essential access information including the gate combination (4585) and instructions to lock the gate upon entry and exit to reach the designated equipment setup area.",
      "categories": [
        "Events",
        "Observing Guide",
        "Practical Information",
        "Astronomy Club"
      ],
      "keywords": [
        "Grant Ranch Star Parties",
        "SJAA",
        "Star Party",
        "Grant Ranch County Park",
        "Mt. Hamilton Road",
        "Directions",
        "Access Code",
        "Observing Location",
        "San Jose Astronomical Association"
      ],
      "pageStart": null,
      "pageEnd": null
    },
    {
      "id": "eph87-06-astro-ads",
      "documentId": "eph87-06",
      "title": "ASTRO ADS",
      "summary": "A new C90 Astro Telescope, complete with a single mount, star diagonal, two eyepieces, a 5x24 finder, and a dew shield, is advertised for sale. The telescope is unused and still in its original shipping cartons, priced at $400 or best offer.",
      "categories": [
        "Advertisement",
        "Equipment Sales",
        "Marketplace"
      ],
      "keywords": [
        "C90 Astro Telescope",
        "telescope for sale",
        "astronomy equipment",
        "used equipment",
        "mount",
        "eyepieces",
        "finder",
        "dew shield"
      ],
      "pageStart": 3,
      "pageEnd": 3
    },
    {
      "id": "eph87-06-yosemite-glacier-point-star-party-sjaa-camping-registration-form",
      "documentId": "eph87-06",
      "title": "YOSEMITE GLACIER POINT STAR PARTY -- SJAA CAMPING REGISTRATION FORM",
      "summary": "The San Jose Astronomical Association (SJAA) is hosting a star party at Yosemite National Park's Glacier Point during the August 22nd weekend, inviting members to present astronomical observations for park guests under favorable conditions. Free group camping for up to 30 people is available at Bridalveil Creek Campground for registered participants, who must comply with park rules regarding telescopes and vehicle parking. Interested members are required to complete and return a registration form to John Gleason.",
      "categories": [
        "Event Announcement",
        "Astronomy Club Activity",
        "Registration Form",
        "Observing Report / Star Party",
        "Camping Information"
      ],
      "keywords": [
        "Yosemite National Park",
        "Glacier Point",
        "Star Party",
        "San Jose Astronomical Association",
        "SJAA",
        "Astronomy",
        "Observing",
        "Camping",
        "Bridalveil Creek Campground",
        "John Gleason",
        "California",
        "August 22nd weekend"
      ],
      "pageStart": 4,
      "pageEnd": 5
    },
    {
      "id": "eph87-06-by-jay-reynolds-freeman",
      "documentId": "eph87-06",
      "title": "BY: JAY REYNOLDS FREEMAN",
      "summary": "Jay Reynolds Freeman recounts his first experience with Kevin Medlock's 30-inch Newtonian telescope at Fremont Peak Observatory, praising its powerful views but detailing significant logistical challenges. He identifies issues with finding objects, observer stability due to climbing ladders, and the need for multiple people to operate the large instrument efficiently. Freeman suggests design improvements like powered observing chairs or better finder placement, with the editor concurring about the ladder issue and mentioning a new platform for groups, while also soliciting donations for finder scopes.",
      "categories": [
        "Observing Report",
        "Equipment Analysis",
        "Opinion Piece",
        "Observatory Operations"
      ],
      "keywords": [
        "30-inch Newtonian",
        "Large aperture telescope",
        "Fremont Peak Observatory",
        "Observing challenges",
        "Finder scopes",
        "Eyepiece selection",
        "Observing comfort",
        "Telescope design improvements",
        "Kevin Medlock",
        "FPOA"
      ],
      "pageStart": null,
      "pageEnd": null
    },
    {
      "id": "eph87-06-by-don-machholz",
      "documentId": "eph87-06",
      "title": "BY: DON MACHHOLZ",
      "summary": "Don Machholz reports on the recent recovery of several faint periodic comets, including Howell (1987h), d'Arrest (1987k), Reinmuth 2 (1987L), and Brooks 2 (1987M), detailing their discovery, current magnitudes, and expected brightness. The article also briefly mentions other bright comets in the sky and the fading of Halley's Comet. Additionally, it provides information about the Comet Rapid Announcement Service (CRAS) for comet enthusiasts.",
      "categories": [
        "Observing Reports",
        "Comets",
        "Astronomy News",
        "Technical"
      ],
      "keywords": [
        "Comets",
        "Comet Recovery",
        "Periodic Comets",
        "Don Machholz",
        "Comet Howell (1987h)",
        "Comet d'Arrest (1987k)",
        "Comet Reinmuth 2 (1987L)",
        "Comet Brooks 2 (1987M)",
        "Halley's Comet",
        "Magnitude",
        "Orbital Period",
        "Comet Rapid Announcement Service (CRAS)"
      ],
      "pageStart": 6,
      "pageEnd": 6
    },
    {
      "id": "eph87-06-ephemerides",
      "documentId": "eph87-06",
      "title": "EPHEMERIDES",
      "summary": "This document provides ephemerides for four comets—Comet Sorrells (1986v), Comet Nishikawa-Takamizawa-Tago (1987c), Comet Wilson (1986L), and Periodic Comet Halley (1982i)—for dates spanning May 25 to July 4. It includes their right ascension, declination, elongation, and magnitude, along with descriptive notes on their orbital characteristics, visibility, distances, and sky movements for observers.",
      "categories": [
        "Ephemerides",
        "Observing Guide",
        "Astronomy",
        "Comet Tracking",
        "Positional Data"
      ],
      "keywords": [
        "Comet Sorrells (1986v)",
        "Comet Nishikawa-Takamizawa-Tago (1987c)",
        "Comet Wilson (1986L)",
        "Periodic Comet Halley (1982i)",
        "Ephemerides",
        "Right Ascension (R.A.)",
        "Declination (DEC)",
        "Magnitude (MAG)",
        "Elongation (ELONG)",
        "Orbital period",
        "Naked-eye visibility",
        "Binocular object",
        "Morning sky",
        "Evening sky",
        "Astronomical Units (AU)"
      ],
      "pageStart": 7,
      "pageEnd": 7
    },
    {
      "id": "eph87-06-seeking-comets",
      "documentId": "eph87-06",
      "title": "SEEKING COMETS",
      "summary": "This article details specific exceptions and conventions for naming comets, particularly concerning the discoverers' names. It explains how periodic comets found by the same person are numbered, how married couples use a single last name for a comet, and how hyphenated or multi-part names (like \"Singer-Brewster\" or \"van Biesbroeck\") are handled. The text provides various examples to clarify these nuanced rules in comet nomenclature.",
      "categories": [
        "astronomy",
        "nomenclature",
        "technical guidelines"
      ],
      "keywords": [
        "comets",
        "naming conventions",
        "discoverers",
        "periodic comets",
        "hyphenated names",
        "compound names",
        "astronomical naming"
      ],
      "pageStart": null,
      "pageEnd": null
    },
    {
      "id": "eph87-06-space-shuttle-recovery-effort-is-progressing",
      "documentId": "eph87-06",
      "title": "SPACE SHUTTLE RECOVERY EFFORT IS PROGRESSING",
      "summary": "The Space Shuttle recovery effort is progressing, with the solid booster redesign complete and sub-scale testing finished; full-scale firing is scheduled for May. NASA has updated the flight resumption target to April 1988, citing a new tank test and readiness firing needs, while a contractor assessment predicts readiness by September 1988.",
      "categories": [
        "Space Exploration",
        "Aerospace Engineering",
        "Program Management",
        "NASA News"
      ],
      "keywords": [
        "Space Shuttle",
        "NASA",
        "Solid Boosters",
        "Recovery Effort",
        "Flight Resumption",
        "Aerospace Testing",
        "Program Schedule"
      ],
      "pageStart": null,
      "pageEnd": null
    },
    {
      "id": "eph87-06-space-station-program-is-shaky-but-still-alive",
      "documentId": "eph87-06",
      "title": "SPACE STATION PROGRAM IS SHAKY BUT STILL ALIVE",
      "summary": "The Space Station Program recently faced a political crisis where a Department of Defense power play almost led to international partners withdrawing, only for NASA's firm stance to resolve the immediate conflict. Despite lingering political tensions, NASA has advanced with requests for hardware proposals, announcing program changes including an electrical power upgrade and an accelerated deployment schedule, targeting permanently manned capability by late 1995.",
      "categories": [
        "Space Program News",
        "Space Policy",
        "Project Management",
        "International Relations"
      ],
      "keywords": [
        "Space Station Program",
        "NASA",
        "Department of Defense",
        "International Partners",
        "Program Changes",
        "Deployment Schedule",
        "Electrical Power",
        "Hardware Proposals",
        "Political Conflict"
      ],
      "pageStart": null,
      "pageEnd": null
    },
    {
      "id": "eph87-06-the-value-of-man-in-space-is-proved-again",
      "documentId": "eph87-06",
      "title": "THE VALUE OF MAN IN SPACE IS PROVED AGAIN",
      "summary": "The Kvant x-ray astrophysics module experienced initial difficulties docking with the Mir space station, with a forgotten bag preventing proper electrical connections. Cosmonauts performed a spacewalk to manually remove the obstruction, enabling a successful docking and electrical hookup. This human intervention ultimately facilitated the first-ever four-vehicle hookup in space with the subsequent arrival of a Progress resupply tanker.",
      "categories": [
        "Space Exploration",
        "Mission Report",
        "Human Spaceflight",
        "Space Station Operations",
        "News"
      ],
      "keywords": [
        "Kvant module",
        "Mir space station",
        "docking",
        "cosmonauts",
        "spacewalk",
        "Progress resupply tanker",
        "USSR",
        "x-ray astrophysics",
        "space mission",
        "human intervention"
      ],
      "pageStart": null,
      "pageEnd": null
    },
    {
      "id": "eph87-06-u-s-and-ussr-having-launch-problems",
      "documentId": "eph87-06",
      "title": "U.S. AND USSR HAVING LAUNCH PROBLEMS",
      "summary": "Both the U.S. and USSR recently experienced significant launch failures. The U.S. lost an Atlas Centaur carrying a Fleet Satellite Communications spacecraft on March 26th due to a lightning strike. The Soviets, on April 24th, also lost a Proton booster carrying three large navigation satellites, marking their second such failure.",
      "categories": [
        "Space News",
        "Launch Failures",
        "Aerospace Industry"
      ],
      "keywords": [
        "Atlas Centaur",
        "Proton booster",
        "launch failure",
        "lightning strike",
        "Fleet Satellite Communications",
        "navigation satellites",
        "U.S. space program",
        "USSR space program"
      ],
      "pageStart": 8,
      "pageEnd": 8
    },
    {
      "id": "eph87-06-by-don-machholz-and-rich-page",
      "documentId": "eph87-06",
      "title": "BY: DON MACHHOLZ AND RICH PAGE",
      "summary": "This article describes a quiet, low-traffic stargazing site on Weaver Road above Lexington Reservoir, near San Jose. Located at 1600 feet, it offers good visibility above valley haze with a limiting naked-eye magnitude of 5.8, despite some light pollution and occasional adverse weather. The site, suitable for about five vehicles and telescopes, is presented as a convenient and potentially favorite spot for local astronomers.",
      "categories": [
        "Observing Reports",
        "Stargazing Locations",
        "Site Reviews"
      ],
      "keywords": [
        "Stargazing",
        "Observing site",
        "Weaver Road",
        "Lexington Reservoir",
        "San Jose",
        "Light pollution",
        "Milky Way",
        "Naked-eye magnitude",
        "Site conditions",
        "Astronomy",
        "California"
      ],
      "pageStart": null,
      "pageEnd": null
    },
    {
      "id": "eph87-06-first-navstar-satellite-delivered",
      "documentId": "eph87-06",
      "title": "FIRST NAVSTAR SATELLITE DELIVERED",
      "summary": "The first Navstar global positioning system satellite has been delivered to the Air Force. This spacecraft will be stored until the new Delta 2 booster becomes available in October 1988 for its eventual launch.",
      "categories": [
        "News",
        "Space Technology",
        "Satellite Systems",
        "Military/Defense"
      ],
      "keywords": [
        "Navstar",
        "GPS",
        "Satellite",
        "Air Force",
        "Delta 2 booster",
        "Spacecraft delivery",
        "Launch preparation"
      ],
      "pageStart": 9,
      "pageEnd": 9
    },
    {
      "id": "eph87-06-general-meetings",
      "documentId": "eph87-06",
      "title": "GENERAL MEETINGS",
      "summary": "The SJAA holds monthly General Meetings at the Los Gatos Red Cross building on the 4th Saturday of each month, starting at 8 PM. These meetings, which also host \"Indoor Star Parties,\" offer a friendly atmosphere for members to share interests in astrophotography, deep sky observation, telescope making, and general astronomy. The article provides detailed directions to the venue.",
      "categories": [
        "Events",
        "Meetings",
        "Logistics",
        "Community Information"
      ],
      "keywords": [
        "SJAA",
        "General Meetings",
        "Los Gatos",
        "Red Cross building",
        "Indoor Star Parties",
        "Astronomy",
        "Astrophotography",
        "Deep Sky Observation",
        "Telescope Making",
        "Monthly Meetings"
      ],
      "pageStart": null,
      "pageEnd": null
    },
    {
      "id": "eph87-06-indoor-star-parties",
      "documentId": "eph87-06",
      "title": "INDOOR STAR PARTIES",
      "summary": "The article describes monthly \"Indoor Star Parties\" hosted by an astronomy organization, providing an informal gathering for amateur astronomers. Attendees are encouraged to bring telescopes and binoculars to share, with activities including outdoor observing, astrophotography slideshows, and an introductory astronomy workshop. These events, held at the Los Gatos Red Cross Building, also serve as a venue for board meetings and social interaction.",
      "categories": [
        "Event Announcement",
        "Club Activities",
        "Astronomy Outreach"
      ],
      "keywords": [
        "Indoor Star Parties",
        "Amateur Astronomy",
        "Telescopes",
        "Binoculars",
        "Astrophotography",
        "Astronomy Workshop",
        "Social Gathering",
        "SJAA"
      ],
      "pageStart": null,
      "pageEnd": null
    },
    {
      "id": "eph87-06-henry-coe-state-park",
      "documentId": "eph87-06",
      "title": "HENRY COE STATE PARK",
      "summary": "This document provides directions to Henry Coe State Park, guiding visitors from Hwy 101 to a specific observing site. It details access to the site via a locked gate, providing the club combination and emphasizing the importance of re-locking. Additionally, it offers crucial advice for those arriving after dark, recommending parking outside the gate and hiking in to find a suitable observing spot.",
      "categories": [
        "Directions",
        "Observing Site Guide",
        "Visitor Information",
        "Astronomy Club Information"
      ],
      "keywords": [
        "Henry Coe State Park",
        "Directions",
        "Observing Site",
        "Gate Combination",
        "SJAA",
        "Morgan Hill",
        "Anderson Reservoir",
        "Astronomy"
      ],
      "pageStart": null,
      "pageEnd": null
    },
    {
      "id": "eph87-06-fremont-peak-state-park",
      "documentId": "eph87-06",
      "title": "FREMONT PEAK STATE PARK",
      "summary": "The article provides detailed directions to Fremont Peak State Park, highlighting it as a popular astronomical observing site often frequented by the San Jose Astronomical Association (SJAA) during clear new moon weekends. It also mentions the Fremont Peak Observatory Association's (FPOA) public observatory located there, accommodating numerous telescopes. Additionally, the document includes publication information for the SJAA's monthly 'EPHEMERIS' newsletter and lists the association's current officers and board members with contact details.",
      "categories": [
        "Observing Site Guide",
        "Astronomical Club Information",
        "Logistics/Directions",
        "Organizational Directory",
        "Newsletter Information"
      ],
      "keywords": [
        "Fremont Peak State Park",
        "San Jose Astronomical Association (SJAA)",
        "Fremont Peak Observatory Association (FPOA)",
        "Astronomy",
        "Observing site",
        "New Moon",
        "Telescopes",
        "Public observatory",
        "EPHEMERIS",
        "Club officers",
        "California"
      ],
      "pageStart": 10,
      "pageEnd": 10
    },
    {
      "id": "eph87-06-san-jose-astronomical-association-membership-application",
      "documentId": "eph87-06",
      "title": "SAN JOSE ASTRONOMICAL ASSOCIATION MEMBERSHIP APPLICATION",
      "summary": "This document is a membership application form for the San Jose Astronomical Association (SJAA). It details different membership tiers, including options for individual membership, membership with a Sky & Telescope subscription, and a junior membership, each with its associated cost. The form also provides submission instructions, including a mailing address and contact information for the association's treasurer.",
      "categories": [
        "Membership Application",
        "Organizational Information",
        "Club/Association"
      ],
      "keywords": [
        "San Jose Astronomical Association",
        "SJAA",
        "Membership",
        "Application",
        "Dues",
        "Fees",
        "Astronomy Club",
        "Contact Information"
      ],
      "pageStart": null,
      "pageEnd": null
    },
    {
      "id": "eph87-06-questionnaire-optional",
      "documentId": "eph87-06",
      "title": "Questionnaire (optional)",
      "summary": "This document is an optional questionnaire designed to solicit information regarding individuals' astronomical interests, whether they own a telescope, and specific areas of astronomy in which they feel qualified to assist others. It also includes mailing information for SJAA EPHEMERIS, a non-profit organization in San Jose, CA, and is marked as time-sensitive news material.",
      "categories": [
        "Questionnaire",
        "Community Engagement",
        "Organizational Document",
        "News / Announcement"
      ],
      "keywords": [
        "astronomical interests",
        "telescope ownership",
        "astronomy expertise",
        "survey",
        "SJAA EPHEMERIS",
        "San Jose",
        "non-profit",
        "member engagement"
      ],
      "pageStart": null,
      "pageEnd": null
    }
  ],
  "documents": [
    {
      "id": "eph87-06",
      "title": "=== PAGE 1 ===",
      "issueDate": null,
      "pdfPath": "8706/Eph87_06.pdf",
      "txtPath": "8706/Eph87_06.md"
    }
  ]
}